ipcrypt/__init__.py
ipcrypt/deterministic.py
ipcrypt/nd.py
ipcrypt/ndx.py
ipcrypt/pfx.py
ipcrypt-0.1.0.dist-info/METADATA
ipcrypt-0.1.0.dist-info/WHEEL
ipcrypt-0.1.0.dist-info/licenses/LICENSE
ipcrypt-0.1.0.dist-info/RECORD
