Metadata-Version: 2.4
Name: ipcrypt
Version: 0.1.0
Summary: IP address encryption and obfuscation methods
Project-URL: Homepage, https://github.com/ipcrypt-std/draft-denis-ipcrypt
Project-URL: Documentation, https://ipcrypt-std.github.io/draft-denis-ipcrypt/
Project-URL: Bug Tracker, https://github.com/ipcrypt-std/draft-denis-ipcrypt/issues
Project-URL: Repository, https://github.com/ipcrypt-std/draft-denis-ipcrypt
Author-email: Frank Denis <github@pureftpd.org>
License: ISC
License-File: LICENSE
Keywords: cryptography,encryption,ip,network,obfuscation,privacy
Classifier: Development Status :: 4 - Beta
Classifier: Intended Audience :: Developers
Classifier: Intended Audience :: System Administrators
Classifier: License :: OSI Approved :: ISC License (ISCL)
Classifier: Operating System :: OS Independent
Classifier: Programming Language :: Python :: 3
Classifier: Programming Language :: Python :: 3.8
Classifier: Programming Language :: Python :: 3.9
Classifier: Programming Language :: Python :: 3.10
Classifier: Programming Language :: Python :: 3.11
Classifier: Programming Language :: Python :: 3.12
Classifier: Topic :: Security :: Cryptography
Classifier: Topic :: System :: Networking
Requires-Python: >=3.8
Requires-Dist: pycryptodome>=3.18.0
Provides-Extra: dev
Requires-Dist: black>=23.0.0; extra == 'dev'
Requires-Dist: pytest-cov>=4.0.0; extra == 'dev'
Requires-Dist: pytest>=7.0.0; extra == 'dev'
Requires-Dist: ruff>=0.1.0; extra == 'dev'
